ohaws/__init__.py
ohaws/s3/main.py
ohaws-0.1.1.dist-info/METADATA
ohaws-0.1.1.dist-info/WHEEL
ohaws-0.1.1.dist-info/top_level.txt
ohaws-0.1.1.dist-info/RECORD
